araali/.__init__.py.swo
araali/.__init__.py.swp
araali/.__main__.py.swn
araali/.__main__.py.swo
araali/.__main__.py.swp
araali/.api.py.swn
araali/.api.py.swo
araali/.api.py.swp
araali/.api_cli.py.swp
araali/.api_grpc.py.swp
araali/.araalictl.py.swo
araali/.araalictl.py.swp
araali/.aws.py.swp
araali/.gitignore
araali/.teleport.py.swp
araali/.utils.py.swn
araali/.utils.py.swo
araali/__init__.py
araali/__main__.py
araali/api.py
araali/api_cli.py
araali/api_grpc.py
araali/araali_api_service_pb2.py
araali/araali_api_service_pb2_grpc.py
araali/araali_api_service_pb2_grpc.py-e
araali/araalictl.py
araali/aws.py
araali/quickstart_api.py
araali/teleport.py
araali/template.py
araali/utils.py
araali-0.0.36.dist-info/METADATA
araali-0.0.36.dist-info/WHEEL
araali-0.0.36.dist-info/licenses/LICENSE
araali-0.0.36.dist-info/RECORD
