Metadata-Version: 2.1
Name: araali
Version: 0.0.36
Summary: Araali API
Project-URL: Homepage, https://github.com/araalinetworks/api/tree/main/python/api
Project-URL: Bug Tracker, https://github.com/araalinetworks/api/issues
Author-email: "Abhishek R. Singh" <abhishek@araalinetworks.com>
License: MIT License
License-File: LICENSE
Classifier: License :: OSI Approved :: MIT License
Classifier: Operating System :: OS Independent
Classifier: Programming Language :: Python :: 3
Requires-Python: >=2.7
Requires-Dist: boto3
Requires-Dist: python-dateutil
Requires-Dist: pyyaml
Requires-Dist: requests
